zooboss/__init__.py
zooboss/__main__.py
zooboss-0.1.0.dist-info/DESCRIPTION.rst
zooboss-0.1.0.dist-info/METADATA
zooboss-0.1.0.dist-info/RECORD
zooboss-0.1.0.dist-info/WHEEL
zooboss-0.1.0.dist-info/entry_points.txt
zooboss-0.1.0.dist-info/metadata.json
zooboss-0.1.0.dist-info/top_level.txt
