Metadata-Version: 2.0
Name: zooboss
Version: 0.1.0
Summary: A malware zoo files organizer
Home-page: https://github.com/neriberto/zooboss
Author: Neriberto C.Prado
Author-email: neriberto@gmail.com
License: BSD 3-Clause License
Platform: UNKNOWN
